luca/__init__.py
luca/charts.py
luca/connectors.py
luca/datasources.py
luca/querys.py
luca/systems.py
luca/users.py
python_luca_bds-1.0.1.dist-info/METADATA
python_luca_bds-1.0.1.dist-info/WHEEL
python_luca_bds-1.0.1.dist-info/top_level.txt
python_luca_bds-1.0.1.dist-info/RECORD
