Metadata-Version: 2.4
Name: python-luca-bds
Version: 1.0.1
Summary: This library provides a set of tools for interacting with the LUCA BDS API. It allows you to perform queries and execute operations in the LUCA environment using secure connections
Author-email: Marcos Cobo Carrillo <mcobo@cic.es>
Project-URL: LUCA BDS, https://luca-bds.com
Project-URL: Documentation, https://docs.luca-bds.com/latest
Project-URL: Source, https://github.com/CIC-SL/python-luca-bds
Project-URL: Changelog, https://github.com/CIC-SL/python-luca-bds/blob/main/CHANGELOG.md
Keywords: LUCA BDS,Data,Analytics
Requires-Python: >=3.9
Requires-Dist: requests
Requires-Dist: python-keycloak
Requires-Dist: pandas
